README.rst
setup.py
allauth_djrill/__init__.py
allauth_djrill/adapter.py
allauth_djrill/tasks.py
django_allauth_djrill.egg-info/PKG-INFO
django_allauth_djrill.egg-info/SOURCES.txt
django_allauth_djrill.egg-info/dependency_links.txt
django_allauth_djrill.egg-info/not-zip-safe
django_allauth_djrill.egg-info/requires.txt
django_allauth_djrill.egg-info/top_level.txt